setup.cfg
setup.py
roguehostapd/__init__.py
roguehostapd/hostapd_constants.py
roguehostapd/hostapd_controller.py
roguehostapd/run.py
test_roguehostapd.egg-info/PKG-INFO
test_roguehostapd.egg-info/SOURCES.txt
test_roguehostapd.egg-info/dependency_links.txt
test_roguehostapd.egg-info/top_level.txt