Metadata-Version: 1.0
Name: test-roguehostapd
Version: 0.1.1
Summary: Hostapd wrapper for hostapd
Home-page: UNKNOWN
Author: Anakin
Author-email: UNKNOWN
License: UNKNOWN
Platform: UNKNOWN
